xmyu/__init__.py
xmyu/xmyu.py
xmyu-0.0.2.dist-info/METADATA
xmyu-0.0.2.dist-info/WHEEL
xmyu-0.0.2.dist-info/top_level.txt
xmyu-0.0.2.dist-info/RECORD
