Metadata-Version: 2.1
Name: xmyu
Version: 0.0.2
Summary: 咸鱼只想占个名字罢辽
Home-page: https://gitee.com/ltfd/a-salted-fish-package.git
Author: LuoTing
Author-email: 977935501@qq.com
